{
  "$schema": "https://cyclonedx.org/schema/tool-center-v2.tool.schema.json",
  "specVersion": "2.0",
  "tool": {
    "name": "docker-sbom-cli-plugin",
    "publisher": "Docker",
    "description": "Docker CLI plugin that generates Software Bills of Materials (SBOMs) for container images using Syft as the underlying scanner, with CycloneDX output support.",
    "repository_url": "https://github.com/docker/sbom-cli-plugin",
    "website_url": "https://github.com/docker/sbom-cli-plugin",
    "capabilities": [
      "SBOM"
    ],
    "availability": [
      "OPEN_SOURCE",
      "OSI_APPROVED"
    ],
    "functions": [
      "AUTHOR",
      "PACKAGE_MANAGER_INTEGRATION"
    ],
    "analysis": [],
    "transform": [
      "BOM_SERIALIZATION_FORMAT"
    ],
    "packaging": [
      "COMMAND_LINE_UTILITY"
    ],
    "library": [
      "GO",
      "SHELL"
    ],
    "platform": [
      "LINUX",
      "MAC",
      "WINDOWS"
    ],
    "lifecycle": [
      "POST-BUILD",
      "DISCOVERY"
    ],
    "supportedStandards": [
      "CYCLONEDX",
      "SPDX"
    ],
    "cycloneDxVersion": [],
    "supportedLanguages": []
  }
}