{
  "$schema": "https://cyclonedx.org/schema/tool-center-v2.tool.schema.json",
  "specVersion": "2.0",
  "tool": {
    "name": "Meterian BOSS scanner",
    "publisher": "Meterian",
    "description": "Software composition analysis that inventories codebases and produces CycloneDX SBOMs while detecting security and licence risks across 12+ ecosystems.",
    "repository_url": "https://github.com/MeterianHQ/meterian-github-action",
    "website_url": "https://meterian.io/products/boss",
    "capabilities": [
      "SBOM",
      "VDR/VEX"
    ],
    "availability": [
      "FREEMIUM",
      "SUBSCRIPTION"
    ],
    "functions": [
      "AUTHOR",
      "ANALYSIS",
      "PACKAGE_MANAGER_INTEGRATION",
      "TRANSFORM"
    ],
    "analysis": [
      "SECURITY_VULNERABILITIES",
      "LICENSE_REPORTING"
    ],
    "transform": [
      "BOM_SERIALIZATION_FORMAT"
    ],
    "packaging": [
      "COMMAND_LINE_UTILITY",
      "GITHUB_ACTION",
      "CONTAINER_IMAGE"
    ],
    "library": [
      "SHELL"
    ],
    "platform": [
      "LINUX",
      "MAC",
      "WINDOWS"
    ],
    "lifecycle": [
      "PRE-BUILD",
      "BUILD",
      "POST-BUILD",
      "OPERATIONS"
    ],
    "supportedStandards": [
      "CYCLONEDX",
      "PACKAGE_URL",
      "CPE"
    ],
    "cycloneDxVersion": [
      "CYCLONEDX_V1.6",
      "CYCLONEDX_V1.5",
      "CYCLONEDX_V1.4"
    ],
    "supportedLanguages": [
      "C/C++",
      "GO",
      "JAVA",
      "JAVASCRIPT/TYPESCRIPT",
      ".NET",
      "NODE.JS",
      "PERL",
      "PHP",
      "PYTHON",
      "RUBY",
      "RUST",
      "SWIFT"
    ]
  }
}