{
  "$schema": "https://cyclonedx.org/schema/tool-center-v2.tool.schema.json",
  "specVersion": "2.0",
  "tool": {
    "name": "NowSecure Platform",
    "publisher": "NowSecure",
    "description": "Mobile application security testing solution that automates static, dynamic and interactive testing, with SBOM capabilities through GitHub integrations",
    "website_url": "https://www.nowsecure.com/products/nowsecure-platform/",
    "capabilities": [
      "SBOM",
      "VDR/VEX"
    ],
    "availability": [
      "COMMERCIAL_LICENSE"
    ],
    "functions": [
      "ANALYSIS",
      "TRANSFORM"
    ],
    "analysis": [
      "SECURITY_VULNERABILITIES",
      "OUTDATED_COMPONENTS"
    ],
    "platform": [
      "LINUX",
      "MAC",
      "WINDOWS"
    ],
    "lifecycle": [
      "BUILD",
      "POST-BUILD",
      "OPERATIONS"
    ],
    "supportedStandards": [
      "CYCLONEDX"
    ]
  }
}