{
  "$schema": "https://cyclonedx.org/schema/tool-center-v2.tool.schema.json",
  "specVersion": "2.0",
  "tool": {
    "name": "Tally",
    "publisher": "Jetstack",
    "description": "Command-line tool that adds OpenSSF Scorecard security posture scores to packages listed in CycloneDX SBOMs.",
    "repository_url": "https://github.com/jetstack/tally",
    "website_url": "https://github.com/jetstack/tally",
    "capabilities": [
      "SBOM"
    ],
    "availability": [
      "OPEN_SOURCE",
      "OSI_APPROVED"
    ],
    "functions": [
      "ANALYSIS"
    ],
    "analysis": [
      "POLICY_EVALUATION"
    ],
    "packaging": [
      "COMMAND_LINE_UTILITY",
      "CONTAINER_IMAGE"
    ],
    "library": [
      "GO"
    ],
    "platform": [
      "LINUX",
      "MAC",
      "WINDOWS"
    ],
    "lifecycle": [
      "POST-BUILD"
    ],
    "supportedStandards": [
      "CYCLONEDX"
    ],
    "cycloneDxVersion": [
      "CYCLONEDX_V1.6"
    ]
  }
}