{
  "$schema": "https://cyclonedx.org/schema/tool-center-v2.tool.schema.json",
  "specVersion": "2.0",
  "tool": {
    "name": "Vuls",
    "publisher": "Future Corp",
    "description": "Agent-less vulnerability scanner for Linux, FreeBSD, containers, WordPress, programming language libraries and network devices which outputs CycloneDX Vulnerability Disclosure Reports (VDR).",
    "repository_url": "https://github.com/future-architect/vuls",
    "website_url": "https://vuls.io/",
    "capabilities": [
      "VDR/VEX"
    ],
    "availability": [
      "OPEN_SOURCE",
      "OSI_APPROVED"
    ],
    "functions": [
      "AUTHOR",
      "ANALYSIS"
    ],
    "analysis": [
      "SECURITY_VULNERABILITIES"
    ],
    "packaging": [
      "COMMAND_LINE_UTILITY",
      "CONTAINER_IMAGE"
    ],
    "library": [
      "GO"
    ],
    "platform": [
      "LINUX",
      "MAC",
      "WINDOWS"
    ],
    "lifecycle": [
      "OPERATIONS",
      "DISCOVERY"
    ],
    "supportedStandards": [
      "CYCLONEDX"
    ]
  }
}